{"game_id":"matchgame-3bd17405-000d-c749-a1f9-0ecc2cdb1803","match_id":"match-6e82a2ef-9c1f-a748-892f-e236bae88cb3","tournament_id":"tournament-9623163a-0f68-9b4e-b84e-c36788117572","tournament_type":"owl","season_id":"2019","game_number":3,"map_id":"0x08000000000001DB","map_type":"ASSAULT","esports_tournament_id":5062,"esports_match_id":21212,"teams":[{"esports_team_id":7692,"stats":[{"name":"deaths","value":64,"id":"0x086000000000002A"}],"players":[{"esports_player_id":8896,"stats":[{"name":"damage","value":8744.300640404224,"id":"0x08600000000001BF"},{"name":"deaths","value":9,"id":"0x086000000000002A"},{"name":"eliminations","value":9,"id":"0x086000000000001F"},{"name":"healing","value":62.33996558189392,"id":"0x08600000000001C1"}],"heroes":[{"hero_id":"0x02E00000000000DD","name":"mei","stats":[{"name":"damage","value":28.125,"id":"0x08600000000001BF"},{"name":"deaths","value":1,"id":"0x086000000000002A"},{"name":"healing","value":62.33996558189392,"id":"0x08600000000001C1"}]},{"hero_id":"0x02E000000000000A","name":"widowmaker","stats":[{"name":"damage","value":2453.2072410583496,"id":"0x08600000000001BF"},{"name":"deaths","value":5,"id":"0x086000000000002A"},{"name":"eliminations","value":2,"id":"0x086000000000001F"}]},{"hero_id":"0x02E0000000000042","name":"mccree","stats":[{"name":"damage","value":1968.8084564208984,"id":"0x08600000000001BF"},{"name":"deaths","value":1,"id":"0x086000000000002A"},{"name":"eliminations","value":3,"id":"0x086000000000001F"}]},{"hero_id":"0x02E000000000012E","name":"sombra","stats":[{"name":"damage","value":2298.5707726478577,"id":"0x08600000000001BF"},{"name":"eliminations","value":4,"id":"0x086000000000001F"}]},{"hero_id":"0x02E0000000000003","name":"tracer","stats":[{"name":"damage","value":1995.5891702771187,"id":"0x08600000000001BF"},{"name":"deaths","value":2,"id":"0x086000000000002A"}]}]},{"esports_player_id":8787,"stats":[{"name":"damage","value":10977.584349751472,"id":"0x08600000000001BF"},{"name":"deaths","value":9,"id":"0x086000000000002A"},{"name":"eliminations","value":16,"id":"0x086000000000001F"}],"heroes":[{"hero_id":"0x02E000000000007A","name":"dva","stats":[{"name":"damage","value":10977.584349751472,"id":"0x08600000000001BF"},{"name":"deaths","value":9,"id":"0x086000000000002A"},{"name":"eliminations","value":16,"id":"0x086000000000001F"}]},{"hero_id":"0x02E0000000000068","name":"zarya","stats":[]}]},{"esports_player_id":8813,"stats":[{"name":"damage","value":3083.486831665039,"id":"0x08600000000001BF"},{"name":"deaths","value":10,"id":"0x086000000000002A"},{"name":"eliminations","value":2,"id":"0x086000000000001F"},{"name":"healing","value":7460.081876277924,"id":"0x08600000000001C1"}],"heroes":[{"hero_id":"0x02E0000000000079","name":"lucio","stats":[{"name":"damage","value":3003.486831665039,"id":"0x08600000000001BF"},{"name":"deaths","value":8,"id":"0x086000000000002A"},{"name":"eliminations","value":2,"id":"0x086000000000001F"},{"name":"healing","value":3181.4207648038864,"id":"0x08600000000001C1"}]},{"hero_id":"0x02E0000000000004","name":"mercy","stats":[{"name":"damage","value":80,"id":"0x08600000000001BF"},{"name":"deaths","value":2,"id":"0x086000000000002A"},{"name":"healing","value":4278.661111474037,"id":"0x08600000000001C1"}]}]},{"esports_player_id":8811,"stats":[{"name":"damage","value":6773.049046993256,"id":"0x08600000000001BF"},{"name":"deaths","value":13,"id":"0x086000000000002A"},{"name":"eliminations","value":6,"id":"0x086000000000001F"},{"name":"healing","value":6222.653885960579,"id":"0x08600000000001C1"}],"heroes":[{"hero_id":"0x02E0000000000005","name":"hanzo","stats":[{"name":"damage","value":1771.351661682129,"id":"0x08600000000001BF"},{"name":"deaths","value":2,"id":"0x086000000000002A"},{"name":"eliminations","value":3,"id":"0x086000000000001F"}]},{"hero_id":"0x02E0000000000195","name":"brigitte","stats":[{"name":"damage","value":3533.616641998291,"id":"0x08600000000001BF"},{"name":"deaths","value":6,"id":"0x086000000000002A"},{"name":"eliminations","value":3,"id":"0x086000000000001F"},{"name":"healing","value":5871.872101902962,"id":"0x08600000000001C1"}]},{"hero_id":"0x02E0000000000016","name":"symmetra","stats":[]},{"hero_id":"0x02E000000000012E","name":"sombra","stats":[{"name":"damage","value":1326.3630855083466,"id":"0x08600000000001BF"},{"name":"deaths","value":4,"id":"0x086000000000002A"},{"name":"healing","value":350.7817840576172,"id":"0x08600000000001C1"}]},{"hero_id":"0x02E0000000000003","name":"tracer","stats":[{"name":"damage","value":141.71765780448914,"id":"0x08600000000001BF"},{"name":"deaths","value":1,"id":"0x086000000000002A"}]}]},{"esports_player_id":8812,"stats":[{"name":"damage","value":9225.327107191086,"id":"0x08600000000001BF"},{"name":"deaths","value":11,"id":"0x086000000000002A"},{"name":"eliminations","value":11,"id":"0x086000000000001F"}],"heroes":[{"hero_id":"0x02E00000000001CA","name":"wreckingball","stats":[{"name":"damage","value":9225.327107191086,"id":"0x08600000000001BF"},{"name":"deaths","value":11,"id":"0x086000000000002A"},{"name":"eliminations","value":11,"id":"0x086000000000001F"}]}]},{"esports_player_id":8772,"stats":[{"name":"damage","value":6722.997918248177,"id":"0x08600000000001BF"},{"name":"deaths","value":12,"id":"0x086000000000002A"},{"name":"eliminations","value":8,"id":"0x086000000000001F"},{"name":"healing","value":9341.490568757057,"id":"0x08600000000001C1"}],"heroes":[{"hero_id":"0x02E00000000001A2","name":"moira","stats":[{"name":"damage","value":1405.6657820940018,"id":"0x08600000000001BF"},{"name":"deaths","value":5,"id":"0x086000000000002A"},{"name":"eliminations","value":2,"id":"0x086000000000001F"},{"name":"healing","value":4489.537251591682,"id":"0x08600000000001C1"}]},{"hero_id":"0x02E0000000000020","name":"zenyatta","stats":[{"name":"damage","value":5317.332136154175,"id":"0x08600000000001BF"},{"name":"deaths","value":7,"id":"0x086000000000002A"},{"name":"eliminations","value":6,"id":"0x086000000000001F"},{"name":"healing","value":4851.953317165375,"id":"0x08600000000001C1"}]}]}]},{"esports_team_id":7699,"stats":[{"name":"deaths","value":22,"id":"0x086000000000002A"}],"players":[{"esports_player_id":8721,"stats":[{"name":"damage","value":7690.506210327148,"id":"0x08600000000001BF"},{"name":"deaths","value":4,"id":"0x086000000000002A"},{"name":"eliminations","value":24,"id":"0x086000000000001F"},{"name":"healing","value":6573.807275295258,"id":"0x08600000000001C1"}],"heroes":[{"hero_id":"0x02E0000000000079","name":"lucio","stats":[{"name":"damage","value":7690.506210327148,"id":"0x08600000000001BF"},{"name":"deaths","value":4,"id":"0x086000000000002A"},{"name":"eliminations","value":24,"id":"0x086000000000001F"},{"name":"healing","value":6573.807275295258,"id":"0x08600000000001C1"}]}]},{"esports_player_id":8724,"stats":[{"name":"damage","value":12490.253938317299,"id":"0x08600000000001BF"},{"name":"deaths","value":3,"id":"0x086000000000002A"},{"name":"eliminations","value":39,"id":"0x086000000000001F"}],"heroes":[{"hero_id":"0x02E00000000001CA","name":"wreckingball","stats":[{"name":"damage","value":8375.790104866028,"id":"0x08600000000001BF"},{"name":"deaths","value":2,"id":"0x086000000000002A"},{"name":"eliminations","value":27,"id":"0x086000000000001F"}]},{"hero_id":"0x02E0000000000009","name":"winston","stats":[{"name":"damage","value":4114.463833451271,"id":"0x08600000000001BF"},{"name":"deaths","value":1,"id":"0x086000000000002A"},{"name":"eliminations","value":12,"id":"0x086000000000001F"}]}]},{"esports_player_id":4671,"stats":[{"name":"damage","value":11186.474002093077,"id":"0x08600000000001BF"},{"name":"deaths","value":3,"id":"0x086000000000002A"},{"name":"eliminations","value":40,"id":"0x086000000000001F"}],"heroes":[{"hero_id":"0x02E000000000007A","name":"dva","stats":[{"name":"damage","value":2988.00547388196,"id":"0x08600000000001BF"},{"name":"deaths","value":1,"id":"0x086000000000002A"},{"name":"eliminations","value":8,"id":"0x086000000000001F"}]},{"hero_id":"0x02E0000000000003","name":"tracer","stats":[{"name":"damage","value":8198.468528211117,"id":"0x08600000000001BF"},{"name":"deaths","value":2,"id":"0x086000000000002A"},{"name":"eliminations","value":32,"id":"0x086000000000001F"}]}]},{"esports_player_id":8723,"stats":[{"name":"damage","value":10390.554157435894,"id":"0x08600000000001BF"},{"name":"deaths","value":5,"id":"0x086000000000002A"},{"name":"eliminations","value":30,"id":"0x086000000000001F"},{"name":"healing","value":2111.076761841774,"id":"0x08600000000001C1"}],"heroes":[{"hero_id":"0x02E0000000000195","name":"brigitte","stats":[{"name":"damage","value":2290.9731636047363,"id":"0x08600000000001BF"},{"name":"deaths","value":1,"id":"0x086000000000002A"},{"name":"eliminations","value":10,"id":"0x086000000000001F"},{"name":"healing","value":2090.0590707063675,"id":"0x08600000000001C1"}]},{"hero_id":"0x02E000000000006E","name":"soldier76","stats":[{"name":"damage","value":458.0407123565674,"id":"0x08600000000001BF"},{"name":"eliminations","value":4,"id":"0x086000000000001F"},{"name":"healing","value":21.017691135406494,"id":"0x08600000000001C1"}]},{"hero_id":"0x02E000000000000A","name":"widowmaker","stats":[{"name":"damage","value":7641.54028147459,"id":"0x08600000000001BF"},{"name":"deaths","value":4,"id":"0x086000000000002A"},{"name":"eliminations","value":16,"id":"0x086000000000001F"}]}]},{"esports_player_id":8725,"stats":[{"name":"damage","value":8348.861230134964,"id":"0x08600000000001BF"},{"name":"deaths","value":3,"id":"0x086000000000002A"},{"name":"eliminations","value":30,"id":"0x086000000000001F"},{"name":"healing","value":11976.729159355164,"id":"0x08600000000001C1"}],"heroes":[{"hero_id":"0x02E000000000013B","name":"ana","stats":[{"name":"damage","value":6457.061230897903,"id":"0x08600000000001BF"},{"name":"deaths","value":3,"id":"0x086000000000002A"},{"name":"eliminations","value":30,"id":"0x086000000000001F"},{"name":"healing","value":10620.19052183628,"id":"0x08600000000001C1"}]},{"hero_id":"0x02E0000000000020","name":"zenyatta","stats":[{"name":"damage","value":1891.7999992370605,"id":"0x08600000000001BF"},{"name":"healing","value":1356.5386375188828,"id":"0x08600000000001C1"}]}]},{"esports_player_id":8722,"stats":[{"name":"damage","value":12370.708604216576,"id":"0x08600000000001BF"},{"name":"deaths","value":4,"id":"0x086000000000002A"},{"name":"eliminations","value":37,"id":"0x086000000000001F"},{"name":"healing","value":510.05108642578125,"id":"0x08600000000001C1"}],"heroes":[{"hero_id":"0x02E000000000012E","name":"sombra","stats":[{"name":"damage","value":12370.708604216576,"id":"0x08600000000001BF"},{"name":"deaths","value":4,"id":"0x086000000000002A"},{"name":"eliminations","value":37,"id":"0x086000000000001F"},{"name":"healing","value":510.05108642578125,"id":"0x08600000000001C1"}]}]}]}],"stats":[{"name":"total_game_time","value":0}]}